[
  {
    "commit": "03d823277e6e1daff5a720c19f6a31b12a7a75a3",
    "Author": "Hans Meine <hans_meine@gmx.net>",
    "Date": "2022-02-22T07:38:24-07:00",
    "orig_timezone": "UTC+01:00",
    "fileTypes": {
      "py": {
        "inserts": 56,
        "deletes": 47,
        "occurrences": 4
      }
    }
  },
  {
    "commit": "be85dc68627a966cd84873f0f0568890486ce805",
    "Author": "Hans Meine <hans_meine@gmx.net>",
    "Date": "2022-02-22T05:00:25-07:00",
    "orig_timezone": "UTC+01:00",
    "fileTypes": {
      "yml": {
        "inserts": 1,
        "deletes": 1,
        "occurrences": 1
      }
    }
  },
  {
    "commit": "d54bf3cfadcb17b05a16d9a4112a138ebc43c625",
    "Author": "Hans Meine <hans_meine@gmx.net>",
    "Date": "2022-02-22T04:57:30-07:00",
    "orig_timezone": "UTC+01:00",
    "fileTypes": {
      "yml": {
        "inserts": 1,
        "deletes": 1,
        "occurrences": 1
      }
    }
  },
  {
    "commit": "77b1b232e706cbe98e67bcddef92179cb7b058db",
    "Author": "Hans Meine <hans_meine@gmx.net>",
    "Date": "2022-02-20T05:25:37-07:00",
    "orig_timezone": "UTC+01:00",
    "fileTypes": {
      "rst": {
        "inserts": 1,
        "deletes": 0,
        "occurrences": 1
      }
    }
  },
  {
    "commit": "485dfadad8d8ede77b3d44cb9b26a90ade203225",
    "Author": "Hans Meine <hans_meine@gmx.net>",
    "Date": "2022-02-20T05:08:50-07:00",
    "orig_timezone": "UTC+01:00",
    "fileTypes": {
      "yml": {
        "inserts": 0,
        "deletes": 8,
        "occurrences": 1
      }
    }
  },
  {
    "commit": "25caa750af7844d1d4aff6f88cfc82eb2c2e1db7",
    "Author": "Hans Meine <hans_meine@gmx.net>",
    "Date": "2022-02-20T05:07:17-07:00",
    "orig_timezone": "UTC+01:00",
    "fileTypes": {
      "yml": {
        "inserts": 3,
        "deletes": 3,
        "occurrences": 1
      }
    }
  },
  {
    "commit": "8e94c6d2ca60df61b15ba47c654d49b42a4e8686",
    "Author": "Hans Meine <hans_meine@gmx.net>",
    "Date": "2022-02-20T05:05:22-07:00",
    "orig_timezone": "UTC+01:00",
    "fileTypes": {
      "yml": {
        "inserts": 0,
        "deletes": 9,
        "occurrences": 1
      }
    }
  },
  {
    "commit": "200672128b2b820bcd15483ce9017f5ae618df01",
    "Author": "Hans Meine <hans_meine@gmx.net>",
    "Date": "2022-02-20T05:04:54-07:00",
    "orig_timezone": "UTC+01:00",
    "fileTypes": {
      "yml": {
        "inserts": 6,
        "deletes": 6,
        "occurrences": 1
      }
    }
  },
  {
    "commit": "ed30205cc7a4d7ee75d9c297cf1d4fef0a89ae21",
    "Author": "Hans Meine <hans_meine@gmx.net>",
    "Date": "2022-02-20T04:58:31-07:00",
    "orig_timezone": "UTC+01:00",
    "fileTypes": {
      "txt": {
        "inserts": 1,
        "deletes": 1,
        "occurrences": 1
      },
      "py": {
        "inserts": 1,
        "deletes": 1,
        "occurrences": 1
      }
    }
  },
  {
    "commit": "16eba6ec5ff8672aaf386224a1781421aa315d9a",
    "Author": "Hans Meine <hans_meine@gmx.net>",
    "Date": "2022-02-20T04:44:31-07:00",
    "orig_timezone": "UTC+01:00",
    "fileTypes": {
      "py": {
        "inserts": 13,
        "deletes": 14,
        "occurrences": 2
      }
    }
  },
  {
    "commit": "4d1d35a5ea077359a13455216c92e5d61b2a354b",
    "Author": "Hans Meine <hans_meine@gmx.net>",
    "Date": "2022-02-20T04:41:12-07:00",
    "orig_timezone": "UTC+01:00",
    "fileTypes": {
      "py": {
        "inserts": 4,
        "deletes": 4,
        "occurrences": 1
      }
    }
  },
  {
    "commit": "4f9af2a01567add2a7d450b6142c886fa4ca7f9f",
    "Author": "Hans Meine <hans_meine@gmx.net>",
    "Date": "2022-02-20T04:39:15-07:00",
    "orig_timezone": "UTC+01:00",
    "fileTypes": {
      "py": {
        "inserts": 66,
        "deletes": 66,
        "occurrences": 2
      }
    }
  },
  {
    "commit": "7c4d019c3ca428b2aa1de9454248a86539a6f6d6",
    "Author": "Hans Meine <hans_meine@gmx.net>",
    "Date": "2022-02-20T04:33:23-07:00",
    "orig_timezone": "UTC+01:00",
    "fileTypes": {
      "py": {
        "inserts": 2,
        "deletes": 2,
        "occurrences": 1
      }
    }
  },
  {
    "commit": "d272711e096b7384aa22d71eb5f9719230320e14",
    "Author": "Hans Meine <hans_meine@gmx.net>",
    "Date": "2022-02-20T04:23:44-07:00",
    "orig_timezone": "UTC+01:00",
    "fileTypes": {
      "py": {
        "inserts": 137,
        "deletes": 142,
        "occurrences": 3
      }
    }
  },
  {
    "commit": "9500d4771850866dee8d64680ddfa8e5153e5810",
    "Author": "Hans Meine <hans_meine@gmx.net>",
    "Date": "2022-02-17T08:40:12-07:00",
    "orig_timezone": "UTC+01:00",
    "fileTypes": {
      "yml": {
        "inserts": 2,
        "deletes": 2,
        "occurrences": 1
      }
    }
  },
  {
    "commit": "2c986dc25d95c3949ddf97c7e1e350f2cc2a4a73",
    "Author": "Hans Meine <hans_meine@gmx.net>",
    "Date": "2022-02-17T08:35:38-07:00",
    "orig_timezone": "UTC+01:00",
    "fileTypes": {
      "py": {
        "inserts": 2,
        "deletes": 2,
        "occurrences": 2
      },
      "rst": {
        "inserts": 5,
        "deletes": 0,
        "occurrences": 1
      }
    }
  },
  {
    "commit": "238148cafbb6cfcf121febebf82eaacc8bf34b1e",
    "Author": "Hans Meine <hans_meine@gmx.net>",
    "Date": "2021-04-25T04:45:42-07:00",
    "orig_timezone": "UTC+02:00",
    "fileTypes": {
      "yml": {
        "inserts": 21,
        "deletes": 0,
        "occurrences": 1
      }
    }
  },
  {
    "commit": "103b6344decdb90846cdc98dfc15b78c3eda73d0",
    "Author": "Pierre-Alain Moret <moret.pierre.alain@gmail.com>",
    "Date": "2021-04-21T04:08:26-07:00",
    "orig_timezone": "UTC+02:00",
    "fileTypes": {
      "py": {
        "inserts": 4,
        "deletes": 2,
        "occurrences": 2
      }
    }
  },
  {
    "commit": "8370360a4af67eda0049f2ec2f74800d9fba4c34",
    "Author": "Hans Meine <hans_meine@gmx.net>",
    "Date": "2021-04-16T08:43:04-07:00",
    "orig_timezone": "UTC+02:00",
    "fileTypes": {
      "py": {
        "inserts": 1,
        "deletes": 7,
        "occurrences": 1
      }
    }
  },
  {
    "commit": "9e2921f394ebc417976ddc6c9ecaec5cbcb7fd29",
    "Author": "Hans Meine <hans_meine@gmx.net>",
    "Date": "2021-04-16T08:42:21-07:00",
    "orig_timezone": "UTC+02:00",
    "fileTypes": {
      "py": {
        "inserts": 39,
        "deletes": 29,
        "occurrences": 1
      }
    }
  },
  {
    "commit": "50f0749ee68c74c939c92610e5f87c5d3202341d",
    "Author": "Hans Meine <hans_meine@gmx.net>",
    "Date": "2021-04-16T08:32:06-07:00",
    "orig_timezone": "UTC+02:00",
    "fileTypes": {
      "yml": {
        "inserts": 3,
        "deletes": 1,
        "occurrences": 1
      }
    }
  },
  {
    "commit": "964383e51a12f4bb56f7bdd603f2eee66b77950d",
    "Author": "Hans Meine <hans_meine@gmx.net>",
    "Date": "2021-04-16T08:28:28-07:00",
    "orig_timezone": "UTC+02:00",
    "fileTypes": {
      "yml": {
        "inserts": 3,
        "deletes": 3,
        "occurrences": 1
      }
    }
  },
  {
    "commit": "49e565e5087393abe9cab73db1e21b4f79a73819",
    "Author": "Hans Meine <hans_meine@gmx.net>",
    "Date": "2021-04-16T08:17:04-07:00",
    "orig_timezone": "UTC+02:00",
    "fileTypes": {
      "yml": {
        "inserts": 10,
        "deletes": 5,
        "occurrences": 1
      }
    }
  },
  {
    "commit": "ede6a70ed4354e668252d50b7415f0e9b2374f22",
    "Author": "Hans Meine <hans_meine@gmx.net>",
    "Date": "2021-04-16T08:06:47-07:00",
    "orig_timezone": "UTC+02:00",
    "fileTypes": {
      "yml": {
        "inserts": 1,
        "deletes": 1,
        "occurrences": 1
      }
    }
  },
  {
    "commit": "57f43e3e5c980370e072ca5d01928d64fefd1f26",
    "Author": "Hans Meine <hans_meine@gmx.net>",
    "Date": "2021-04-16T08:03:21-07:00",
    "orig_timezone": "UTC+02:00",
    "fileTypes": {
      "yml": {
        "inserts": 7,
        "deletes": 0,
        "occurrences": 1
      }
    }
  },
  {
    "commit": "5c4a4de5dff7dca386d2e7f51acb4024a1bf2b39",
    "Author": "Hans Meine <hans_meine@gmx.net>",
    "Date": "2021-04-16T07:41:07-07:00",
    "orig_timezone": "UTC+02:00",
    "fileTypes": {
      "yml": {
        "inserts": 1,
        "deletes": 0,
        "occurrences": 1
      }
    }
  },
  {
    "commit": "025e46a2f9ac7a05bdc18479120f21b96745076c",
    "Author": "Hans Meine <hans_meine@gmx.net>",
    "Date": "2021-04-16T06:35:34-07:00",
    "orig_timezone": "UTC+02:00",
    "fileTypes": {
      "yml": {
        "inserts": 2,
        "deletes": 1,
        "occurrences": 1
      }
    }
  },
  {
    "commit": "7b8172f1a4a59f5696166597c509f8809c253c42",
    "Author": "Hans Meine <hans_meine@gmx.net>",
    "Date": "2021-04-16T06:34:18-07:00",
    "orig_timezone": "UTC+02:00",
    "fileTypes": {
      "noexttext": {
        "inserts": 2,
        "deletes": 0,
        "occurrences": 1
      },
      "py": {
        "inserts": 63,
        "deletes": 39,
        "occurrences": 4
      }
    }
  },
  {
    "commit": "f788cfda282acad269e647da2acb65bcfd24a8b7",
    "Author": "Hans Meine <hans_meine@gmx.net>",
    "Date": "2021-04-16T04:03:21-07:00",
    "orig_timezone": "UTC+02:00",
    "fileTypes": {
      "py": {
        "inserts": 3,
        "deletes": 3,
        "occurrences": 1
      }
    }
  },
  {
    "commit": "8de8a1b5c0e5afc97fa5f8fa03426bc1aa89629a",
    "Author": "Hans Meine <hans_meine@gmx.net>",
    "Date": "2021-04-16T04:02:17-07:00",
    "orig_timezone": "UTC+02:00",
    "fileTypes": {
      "py": {
        "inserts": 0,
        "deletes": 1,
        "occurrences": 1
      }
    }
  },
  {
    "commit": "564e424a7939a90f10a56221bf9b433828e4ea00",
    "Author": "Hans Meine <hans_meine@gmx.net>",
    "Date": "2021-04-16T04:01:14-07:00",
    "orig_timezone": "UTC+02:00",
    "fileTypes": {
      "py": {
        "inserts": 2,
        "deletes": 1,
        "occurrences": 1
      }
    }
  },
  {
    "commit": "3e6546ab0b6feea7f5178726dd5db8604963dec7",
    "Author": "Hans Meine <hans_meine@gmx.net>",
    "Date": "2021-04-16T03:48:34-07:00",
    "orig_timezone": "UTC+02:00",
    "fileTypes": {
      "rst": {
        "inserts": 3,
        "deletes": 0,
        "occurrences": 1
      }
    }
  },
  {
    "commit": "a37f9f0392446673305b68cb1e5e6108158dc5ab",
    "Author": "Hans Meine <hans_meine@gmx.net>",
    "Date": "2021-04-16T03:48:01-07:00",
    "orig_timezone": "UTC+02:00",
    "fileTypes": {
      "rst": {
        "inserts": 2,
        "deletes": 2,
        "occurrences": 1
      }
    }
  },
  {
    "commit": "c07f2699863d92330a26b56a4dbc6f6e65e577e5",
    "Author": "Hans Meine <hans_meine@gmx.net>",
    "Date": "2020-02-21T09:38:30-07:00",
    "orig_timezone": "UTC+01:00",
    "fileTypes": {
      "py": {
        "inserts": 4,
        "deletes": 3,
        "occurrences": 1
      }
    }
  },
  {
    "commit": "40f121d8b8c26f17149457e0443a3128b9a1b751",
    "Author": "Hans Meine <hans_meine@gmx.net>",
    "Date": "2020-02-21T09:37:25-07:00",
    "orig_timezone": "UTC+01:00",
    "fileTypes": {
      "py": {
        "inserts": 13,
        "deletes": 7,
        "occurrences": 1
      }
    }
  },
  {
    "commit": "894cdfede29b1c8e423d26b363d96b66a205a938",
    "Author": "Hans Meine <hans_meine@gmx.net>",
    "Date": "2020-02-19T05:41:13-07:00",
    "orig_timezone": "UTC+01:00",
    "fileTypes": {
      "yml": {
        "inserts": 0,
        "deletes": 17,
        "occurrences": 1
      }
    }
  },
  {
    "commit": "24ed16690662d6a2f47d6ddb753bfb7e3e91e531",
    "Author": "Hans Meine <hans_meine@gmx.net>",
    "Date": "2020-02-19T05:34:12-07:00",
    "orig_timezone": "UTC+01:00",
    "fileTypes": {
      "yml": {
        "inserts": 42,
        "deletes": 5,
        "occurrences": 1
      }
    }
  },
  {
    "commit": "024670498e8bddd7b2427040f584be89ffe222fd",
    "Author": "Hans Meine <hans_meine@gmx.net>",
    "Date": "2020-02-19T04:10:14-07:00",
    "orig_timezone": "UTC+01:00",
    "fileTypes": {
      "txt": {
        "inserts": 1,
        "deletes": 0,
        "occurrences": 1
      }
    }
  },
  {
    "commit": "d065c636b6e3c6f0a9dbf23040a999195130213d",
    "Author": "Hans Meine <hans_meine@gmx.net>",
    "Date": "2020-02-19T04:01:51-07:00",
    "orig_timezone": "UTC+01:00",
    "fileTypes": {
      "yml": {
        "inserts": 1,
        "deletes": 1,
        "occurrences": 1
      }
    }
  },
  {
    "commit": "548e280d78d5b61eede474018fe828aef1523bfc",
    "Author": "Hans Meine <hans_meine@gmx.net>",
    "Date": "2020-02-19T04:00:04-07:00",
    "orig_timezone": "UTC+01:00",
    "fileTypes": {
      "yml": {
        "inserts": 23,
        "deletes": 0,
        "occurrences": 1
      }
    }
  },
  {
    "commit": "92cad2a2a9392b242fcc0a37df3ddac592d5c100",
    "Author": "Hans Meine <hans_meine@gmx.net>",
    "Date": "2020-02-19T02:52:28-07:00",
    "orig_timezone": "UTC+01:00",
    "fileTypes": {
      "py": {
        "inserts": 2,
        "deletes": 1,
        "occurrences": 1
      }
    }
  },
  {
    "commit": "9a3d08fbb478186e444d4c7957c27365444e736e",
    "Author": "Hans Meine <hans_meine@gmx.net>",
    "Date": "2020-02-19T02:37:18-07:00",
    "orig_timezone": "UTC+01:00",
    "fileTypes": {
      "txt": {
        "inserts": 3,
        "deletes": 0,
        "occurrences": 1
      }
    }
  },
  {
    "commit": "332e704817eb232c71fd8cb75de84145c840e329",
    "Author": "Hans Meine <hans_meine@gmx.net>",
    "Date": "2020-02-19T02:33:48-07:00",
    "orig_timezone": "UTC+01:00",
    "fileTypes": {
      "py": {
        "inserts": 1,
        "deletes": 1,
        "occurrences": 1
      }
    }
  },
  {
    "commit": "b5bb25ba6122c174d91675f605792a0cb9da3111",
    "Author": "Hans Meine <hans_meine@gmx.net>",
    "Date": "2020-02-19T02:29:48-07:00",
    "orig_timezone": "UTC+01:00",
    "fileTypes": {
      "rst": {
        "inserts": 3,
        "deletes": 0,
        "occurrences": 1
      },
      "py": {
        "inserts": 1,
        "deletes": 1,
        "occurrences": 1
      }
    }
  },
  {
    "commit": "891da580e5a21cfbac07edba9719b755e322c03a",
    "Author": "Hans Meine <hans_meine@gmx.net>",
    "Date": "2020-02-18T12:06:42-07:00",
    "orig_timezone": "UTC+01:00",
    "fileTypes": {
      "py": {
        "inserts": 8,
        "deletes": 1,
        "occurrences": 1
      }
    }
  },
  {
    "commit": "6fb97240c234cb110cce6d48386f5660966522f9",
    "Author": "Hans Meine <hans_meine@gmx.net>",
    "Date": "2020-02-18T12:05:40-07:00",
    "orig_timezone": "UTC+01:00",
    "fileTypes": {
      "py": {
        "inserts": 17,
        "deletes": 0,
        "occurrences": 1
      }
    }
  },
  {
    "commit": "faa8b2d9e0cdc19471b317390228f2d715cb1cd9",
    "Author": "Hans Meine <hans_meine@gmx.net>",
    "Date": "2020-02-18T11:59:18-07:00",
    "orig_timezone": "UTC+01:00",
    "fileTypes": {
      "rst": {
        "inserts": 1,
        "deletes": 1,
        "occurrences": 1
      }
    }
  },
  {
    "commit": "fd97ca530267d995b4a8e347b3170f4ad42e963b",
    "Author": "Hans Meine <hans_meine@gmx.net>",
    "Date": "2019-12-25T07:51:01-07:00",
    "orig_timezone": "UTC+01:00",
    "fileTypes": {
      "rst": {
        "inserts": 3,
        "deletes": 0,
        "occurrences": 1
      },
      "py": {
        "inserts": 1,
        "deletes": 1,
        "occurrences": 1
      }
    }
  },
  {
    "commit": "6219a61c750c7b6fb8d3fb9a84f16e78588f68d1",
    "Author": "Hans Meine <hans_meine@gmx.net>",
    "Date": "2019-12-25T07:50:07-07:00",
    "orig_timezone": "UTC+01:00",
    "fileTypes": {
      "py": {
        "inserts": 14,
        "deletes": 5,
        "occurrences": 2
      }
    }
  },
  {
    "commit": "1afdba4842034527f86bf9804db1ae11714cebe8",
    "Author": "Hans Meine <hans_meine@gmx.net>",
    "Date": "2019-12-24T05:53:04-07:00",
    "orig_timezone": "UTC+01:00",
    "fileTypes": {
      "rst": {
        "inserts": 3,
        "deletes": 0,
        "occurrences": 1
      },
      "py": {
        "inserts": 1,
        "deletes": 1,
        "occurrences": 1
      }
    }
  },
  {
    "commit": "277b40719add0fa67b8b00fef36b0f48c4d40cb2",
    "Author": "Hans Meine <hans_meine@gmx.net>",
    "Date": "2019-12-24T05:50:46-07:00",
    "orig_timezone": "UTC+01:00",
    "fileTypes": {
      "py": {
        "inserts": 4,
        "deletes": 1,
        "occurrences": 1
      }
    }
  },
  {
    "commit": "9a3d6f51f9e3109df7427fb7f38ad7633805a00a",
    "Author": "Hans Meine <hans_meine@gmx.net>",
    "Date": "2019-12-24T05:44:34-07:00",
    "orig_timezone": "UTC+01:00",
    "fileTypes": {
      "py": {
        "inserts": 12,
        "deletes": 0,
        "occurrences": 1
      }
    }
  },
  {
    "commit": "7bb263a6180304d07a29381fa0d364cac2853b00",
    "Author": "Hans Meine <hans_meine@gmx.net>",
    "Date": "2019-07-15T01:48:32-07:00",
    "orig_timezone": "UTC+02:00",
    "fileTypes": {
      "py": {
        "inserts": 46,
        "deletes": 6,
        "occurrences": 1
      }
    }
  },
  {
    "commit": "7d2f95e18ee2c2ea2d785f921aa4b916c0c9fe62",
    "Author": "Hans Meine <hans_meine@gmx.net>",
    "Date": "2019-07-15T01:45:28-07:00",
    "orig_timezone": "UTC+02:00",
    "fileTypes": {
      "py": {
        "inserts": 12,
        "deletes": 11,
        "occurrences": 2
      }
    }
  },
  {
    "commit": "789e794c837e1e2b216367f955d6b1d9e18531bf",
    "Author": "Hans Meine <hans_meine@gmx.net>",
    "Date": "2019-07-14T06:06:58-07:00",
    "orig_timezone": "UTC+02:00",
    "fileTypes": {
      "py": {
        "inserts": 20,
        "deletes": 0,
        "occurrences": 1
      }
    }
  },
  {
    "commit": "2cc3f9dabc44336b8b2f4d733fc83c543ae73104",
    "Author": "Hans Meine <hans_meine@gmx.net>",
    "Date": "2019-07-14T05:48:39-07:00",
    "orig_timezone": "UTC+02:00",
    "fileTypes": {
      "py": {
        "inserts": 40,
        "deletes": 57,
        "occurrences": 1
      }
    }
  },
  {
    "commit": "d1c494e599c231a96d2eb07f642a7cc61b25efd1",
    "Author": "Hans Meine <hans_meine@gmx.net>",
    "Date": "2019-07-14T04:59:08-07:00",
    "orig_timezone": "UTC+02:00",
    "fileTypes": {
      "py": {
        "inserts": 20,
        "deletes": 0,
        "occurrences": 1
      }
    }
  },
  {
    "commit": "45212e6da6d3844ed05196e0ed9488e026513286",
    "Author": "Hans Meine <hans_meine@gmx.net>",
    "Date": "2019-07-14T04:48:58-07:00",
    "orig_timezone": "UTC+02:00",
    "fileTypes": {
      "py": {
        "inserts": 5,
        "deletes": 5,
        "occurrences": 1
      }
    }
  },
  {
    "commit": "de3c4a45b263dec5053bc32119171eb1112d7752",
    "Author": "Hans Meine <hans_meine@gmx.net>",
    "Date": "2019-07-14T04:35:01-07:00",
    "orig_timezone": "UTC+02:00",
    "fileTypes": {
      "py": {
        "inserts": 39,
        "deletes": 36,
        "occurrences": 1
      }
    }
  },
  {
    "commit": "cb053558ecb476f29c7fc1c2d4aa5380878d5958",
    "Author": "Hans Meine <hans_meine@gmx.net>",
    "Date": "2019-07-13T14:45:14-07:00",
    "orig_timezone": "UTC+02:00",
    "fileTypes": {
      "py": {
        "inserts": 14,
        "deletes": 0,
        "occurrences": 1
      }
    }
  },
  {
    "commit": "b2708a24fd8ea826d5beb97032bdefe63e6663c4",
    "Author": "Hans Meine <hans_meine@gmx.net>",
    "Date": "2019-07-13T14:39:45-07:00",
    "orig_timezone": "UTC+02:00",
    "fileTypes": {
      "py": {
        "inserts": 12,
        "deletes": 0,
        "occurrences": 1
      }
    }
  },
  {
    "commit": "1089457b8153de0fe1c7797c9e92e61f05e5eccd",
    "Author": "Hans Meine <hans_meine@gmx.net>",
    "Date": "2019-07-13T14:37:38-07:00",
    "orig_timezone": "UTC+02:00",
    "fileTypes": {
      "py": {
        "inserts": 12,
        "deletes": 0,
        "occurrences": 1
      }
    }
  },
  {
    "commit": "9a6c63b1dad8061123aab6249c2adaf6881fcd16",
    "Author": "Hans Meine <hans_meine@gmx.net>",
    "Date": "2019-07-13T14:34:57-07:00",
    "orig_timezone": "UTC+02:00",
    "fileTypes": {
      "py": {
        "inserts": 3,
        "deletes": 1,
        "occurrences": 1
      }
    }
  },
  {
    "commit": "023f3c67f90e646ce2fd80418fed85b9c7660bfc",
    "Author": "Hans Meine <hans_meine@gmx.net>",
    "Date": "2019-03-14T08:27:35-07:00",
    "orig_timezone": "UTC+01:00",
    "fileTypes": {
      "rst": {
        "inserts": 1,
        "deletes": 0,
        "occurrences": 1
      },
      "py": {
        "inserts": 1,
        "deletes": 1,
        "occurrences": 1
      }
    }
  },
  {
    "commit": "515a9edfe24d08073a9a072051de8f14775babd2",
    "Author": "Hans Meine <hans_meine@gmx.net>",
    "Date": "2019-03-14T08:18:40-07:00",
    "orig_timezone": "UTC+01:00",
    "fileTypes": {
      "py": {
        "inserts": 22,
        "deletes": 0,
        "occurrences": 2
      }
    }
  },
  {
    "commit": "aada5d3d6025e1a2dfcd0e1c6414e62a00d24bea",
    "Author": "Hans Meine <hans_meine@gmx.net>",
    "Date": "2019-03-14T03:25:39-07:00",
    "orig_timezone": "UTC+01:00",
    "fileTypes": {
      "py": {
        "inserts": 7,
        "deletes": 7,
        "occurrences": 1
      }
    }
  },
  {
    "commit": "dc3ba0f177ece0e3e37f690965c8cc74129137ec",
    "Author": "Hans Meine <hans_meine@gmx.net>",
    "Date": "2019-03-14T03:16:44-07:00",
    "orig_timezone": "UTC+01:00",
    "fileTypes": {
      "py": {
        "inserts": 9,
        "deletes": 5,
        "occurrences": 2
      }
    }
  },
  {
    "commit": "4366236c1108a8450ee6cd0376c3dd6fb65824a9",
    "Author": "Hans Meine <hans_meine@gmx.net>",
    "Date": "2019-03-14T03:16:24-07:00",
    "orig_timezone": "UTC+01:00",
    "fileTypes": {
      "py": {
        "inserts": 25,
        "deletes": 19,
        "occurrences": 1
      }
    }
  },
  {
    "commit": "25f7758418a35e5e651c6fbad738a5b35f758f92",
    "Author": "Hans Meine <hans_meine@gmx.net>",
    "Date": "2019-03-14T02:34:15-07:00",
    "orig_timezone": "UTC+01:00",
    "fileTypes": {
      "py": {
        "inserts": 10,
        "deletes": 0,
        "occurrences": 1
      }
    }
  },
  {
    "commit": "91bcc6b3991fc2a410849e826959fd8ef1e88e20",
    "Author": "Hans Meine <hans_meine@gmx.net>",
    "Date": "2019-03-14T02:33:48-07:00",
    "orig_timezone": "UTC+01:00",
    "fileTypes": {
      "py": {
        "inserts": 10,
        "deletes": 4,
        "occurrences": 1
      }
    }
  },
  {
    "commit": "796b7ac0d6421a2a4129d85eaed7e29e110d7e74",
    "Author": "Hans Meine <hans_meine@gmx.net>",
    "Date": "2019-03-13T04:47:14-07:00",
    "orig_timezone": "UTC+01:00",
    "fileTypes": {
      "rst": {
        "inserts": 3,
        "deletes": 0,
        "occurrences": 1
      },
      "py": {
        "inserts": 11,
        "deletes": 1,
        "occurrences": 2
      }
    }
  },
  {
    "commit": "32f826fbd1659ef1925697fa439080592113635a",
    "Author": "Hans Meine <hans_meine@gmx.net>",
    "Date": "2018-08-11T03:00:14-07:00",
    "orig_timezone": "UTC+02:00",
    "fileTypes": {
      "py": {
        "inserts": 1,
        "deletes": 1,
        "occurrences": 1
      }
    }
  },
  {
    "commit": "0ddd0d9705fa1dff89687888011059b80c4fac8b",
    "Author": "Hans Meine <hans_meine@gmx.net>",
    "Date": "2018-08-11T02:58:04-07:00",
    "orig_timezone": "UTC+02:00",
    "fileTypes": {
      "rst": {
        "inserts": 7,
        "deletes": 3,
        "occurrences": 1
      }
    }
  },
  {
    "commit": "a22fcbf4fb175512c519cd7dc1718a745321b580",
    "Author": "Robert McLeod <robbmcleod@gmail.com>",
    "Date": "2018-04-28T10:55:25-07:00",
    "orig_timezone": "UTC-07:00",
    "fileTypes": {
      "py": {
        "inserts": 6,
        "deletes": 3,
        "occurrences": 2
      }
    }
  },
  {
    "commit": "2f29bc9755b853b0168fa77f0b2fd56bfb271fc4",
    "Author": "Hans Meine <hans_meine@gmx.net>",
    "Date": "2017-08-16T08:59:35-07:00",
    "orig_timezone": "UTC+02:00",
    "fileTypes": {
      "py": {
        "inserts": 2,
        "deletes": 2,
        "occurrences": 1
      }
    }
  },
  {
    "commit": "6da0ee5187279f3405c0eb8e11ac1d348ec61cb1",
    "Author": "John Kirkham <kirkhamj@janelia.hhmi.org>",
    "Date": "2016-11-07T07:50:35-07:00",
    "orig_timezone": "UTC-05:00",
    "fileTypes": {
      "in": {
        "inserts": 1,
        "deletes": 0,
        "occurrences": 1
      }
    }
  },
  {
    "commit": "5e10cb48295394feb1afb23aa656efe1e42360d7",
    "Author": "Hans Meine <hans_meine@gmx.net>",
    "Date": "2016-03-18T00:41:30-07:00",
    "orig_timezone": "UTC+01:00",
    "fileTypes": {
      "py": {
        "inserts": 3,
        "deletes": 0,
        "occurrences": 1
      }
    }
  },
  {
    "commit": "b522bd58389ef9ce094c372eb69f27099e1fc62f",
    "Author": "Hans Meine <hans_meine@gmx.net>",
    "Date": "2016-03-17T23:05:23-07:00",
    "orig_timezone": "UTC+01:00",
    "fileTypes": {
      "rst": {
        "inserts": 3,
        "deletes": 0,
        "occurrences": 1
      },
      "py": {
        "inserts": 1,
        "deletes": 1,
        "occurrences": 1
      }
    }
  },
  {
    "commit": "98c4c7f996e64220f489b75bd1e881e0acb80684",
    "Author": "Hans Meine <hans_meine@gmx.net>",
    "Date": "2016-03-16T02:38:22-07:00",
    "orig_timezone": "UTC+01:00",
    "fileTypes": {
      "py": {
        "inserts": 5,
        "deletes": 3,
        "occurrences": 1
      }
    }
  },
  {
    "commit": "1f300aa7b852788a9cb291282eb2447c390d4ac9",
    "Author": "Hans Meine <hans_meine@gmx.net>",
    "Date": "2016-02-17T01:35:13-07:00",
    "orig_timezone": "UTC+01:00",
    "fileTypes": {
      "rst": {
        "inserts": 3,
        "deletes": 0,
        "occurrences": 1
      },
      "py": {
        "inserts": 1,
        "deletes": 1,
        "occurrences": 1
      }
    }
  },
  {
    "commit": "87548b6867b810ab50dedc94a329ef45cbd83f86",
    "Author": "Hans Meine <hans_meine@gmx.net>",
    "Date": "2015-06-12T03:18:55-07:00",
    "orig_timezone": "UTC+02:00",
    "fileTypes": {
      "rst": {
        "inserts": 1,
        "deletes": 1,
        "occurrences": 1
      }
    }
  },
  {
    "commit": "04be1d4009da6cdfdd01c3a69e4511ab1251625a",
    "Author": "Hans Meine <hans_meine@gmx.net>",
    "Date": "2015-06-12T00:16:51-07:00",
    "orig_timezone": "UTC+02:00",
    "fileTypes": {
      "rst": {
        "inserts": 13,
        "deletes": 7,
        "occurrences": 2
      },
      "py": {
        "inserts": 8,
        "deletes": 3,
        "occurrences": 1
      }
    }
  },
  {
    "commit": "b4ef315a00990ae59caac0d90977404813866944",
    "Author": "Hans Meine <hans_meine@gmx.net>",
    "Date": "2015-06-12T00:10:31-07:00",
    "orig_timezone": "UTC+02:00",
    "fileTypes": {
      "py": {
        "inserts": 2,
        "deletes": 19,
        "occurrences": 1
      }
    }
  },
  {
    "commit": "8a0c177c1c5b3c274b1af67443a14d3d1a18f623",
    "Author": "Hans Meine <hans_meine@gmx.net>",
    "Date": "2015-06-11T23:47:40-07:00",
    "orig_timezone": "UTC+02:00",
    "fileTypes": {
      "py": {
        "inserts": 1,
        "deletes": 1,
        "occurrences": 1
      }
    }
  },
  {
    "commit": "5954ccce77c8437f753d865049699a519aef7af1",
    "Author": "Hans Meine <hans_meine@gmx.net>",
    "Date": "2015-06-11T22:48:36-07:00",
    "orig_timezone": "UTC+02:00",
    "fileTypes": {
      "rst": {
        "inserts": 4,
        "deletes": 3,
        "occurrences": 1
      }
    }
  },
  {
    "commit": "05d237d3502079bc7ccff4e3d178a21e0f9248cb",
    "Author": "Hans Meine <hans_meine@gmx.net>",
    "Date": "2015-06-11T22:48:18-07:00",
    "orig_timezone": "UTC+02:00",
    "fileTypes": {
      "rst": {
        "inserts": 15,
        "deletes": 4,
        "occurrences": 1
      }
    }
  },
  {
    "commit": "231e8ea8787ea838321400e5fcc939b3e77c10ba",
    "Author": "Hans Meine <hans_meine@gmx.net>",
    "Date": "2015-06-11T22:37:14-07:00",
    "orig_timezone": "UTC+02:00",
    "fileTypes": {
      "rst": {
        "inserts": 5,
        "deletes": 2,
        "occurrences": 2
      },
      "py": {
        "inserts": 1,
        "deletes": 1,
        "occurrences": 1
      }
    }
  },
  {
    "commit": "05d860669640a251a85ccb59f4aa25b23ab4add2",
    "Author": "Hans Meine <hans_meine@gmx.net>",
    "Date": "2015-06-11T22:37:39-07:00",
    "orig_timezone": "UTC+02:00",
    "fileTypes": {
      "py": {
        "inserts": 1,
        "deletes": 1,
        "occurrences": 1
      }
    }
  },
  {
    "commit": "b3e50ba248eca25f10775fc2db6cc67602753548",
    "Author": "Rudolf Hoefler <rudolf.hoefler@gmail.com>",
    "Date": "2015-02-22T12:03:44-07:00",
    "orig_timezone": "UTC+01:00",
    "fileTypes": {
      "py": {
        "inserts": 58,
        "deletes": 25,
        "occurrences": 4
      }
    }
  },
  {
    "commit": "cae03fac1a6ab0046c7327e7add769b5e7538c11",
    "Author": "Hans Meine <hans_meine@gmx.net>",
    "Date": "2015-06-11T10:49:25-07:00",
    "orig_timezone": "UTC+02:00",
    "fileTypes": {
      "py": {
        "inserts": 2,
        "deletes": 1,
        "occurrences": 1
      }
    }
  },
  {
    "commit": "c28d364a38ba7f77b273799b69d19af2b40424fa",
    "Author": "Hans Meine <hans_meine@gmx.net>",
    "Date": "2015-06-11T10:47:57-07:00",
    "orig_timezone": "UTC+02:00",
    "fileTypes": {
      "py": {
        "inserts": 2,
        "deletes": 1,
        "occurrences": 1
      }
    }
  },
  {
    "commit": "72cfd0aa381e8602a32fa0671c23b98cacd00b10",
    "Author": "Hans Meine <hans_meine@gmx.net>",
    "Date": "2015-06-11T10:47:40-07:00",
    "orig_timezone": "UTC+02:00",
    "fileTypes": {
      "py": {
        "inserts": 2,
        "deletes": 2,
        "occurrences": 1
      }
    }
  },
  {
    "commit": "d22ea3b26eff04eabad9188d60fc781d1180ecb8",
    "Author": "Hans Meine <hans_meine@gmx.net>",
    "Date": "2015-06-11T10:45:09-07:00",
    "orig_timezone": "UTC+02:00",
    "fileTypes": {
      "py": {
        "inserts": 4,
        "deletes": 3,
        "occurrences": 1
      }
    }
  },
  {
    "commit": "10cc670cce8ee37d2aadb4cf28e9bde6cfdea037",
    "Author": "Hans Meine <hans_meine@gmx.net>",
    "Date": "2014-10-16T02:22:38-07:00",
    "orig_timezone": "UTC+02:00",
    "fileTypes": {
      "py": {
        "inserts": 18,
        "deletes": 1,
        "occurrences": 2
      }
    }
  },
  {
    "commit": "dee7dc2405f7d21127d8f670ea59bc42ac253f59",
    "Author": "Hans Meine <hans_meine@gmx.net>",
    "Date": "2014-10-16T02:20:20-07:00",
    "orig_timezone": "UTC+02:00",
    "fileTypes": {
      "py": {
        "inserts": 30,
        "deletes": 3,
        "occurrences": 2
      }
    }
  },
  {
    "commit": "013f621b374cface4814134d0d2de43412002862",
    "Author": "Hans Meine <hans_meine@gmx.net>",
    "Date": "2014-10-16T02:08:15-07:00",
    "orig_timezone": "UTC+02:00",
    "fileTypes": {
      "py": {
        "inserts": 16,
        "deletes": 1,
        "occurrences": 2
      }
    }
  },
  {
    "commit": "aa2be555296b113ef41bc49c5ba8b0096d102ee0",
    "Author": "groakat <p.rennert@cs.ucl.ac.uk>",
    "Date": "2015-04-22T23:30:50-07:00",
    "orig_timezone": "UTC+01:00",
    "fileTypes": {
      "py": {
        "inserts": 1,
        "deletes": 1,
        "occurrences": 1
      }
    }
  },
  {
    "commit": "1356324e9b285ffbe4cd4c86bdde33b66c83aa00",
    "Author": "Hans Meine <hans_meine@gmx.net>",
    "Date": "2014-08-26T08:43:47-07:00",
    "orig_timezone": "UTC+02:00",
    "fileTypes": {
      "py": {
        "inserts": 7,
        "deletes": 1,
        "occurrences": 1
      }
    }
  },
  {
    "commit": "c589d76843f367f006001d95156faa071ff532f7",
    "Author": "Hans Meine <hans_meine@gmx.net>",
    "Date": "2014-08-20T01:34:34-07:00",
    "orig_timezone": "UTC+02:00",
    "fileTypes": {
      "rst": {
        "inserts": 1,
        "deletes": 1,
        "occurrences": 1
      }
    }
  },
  {
    "commit": "c6a364c5d43f053081007a75de90889c0a630dd4",
    "Author": "Hans Meine <hans_meine@gmx.net>",
    "Date": "2014-08-20T00:39:27-07:00",
    "orig_timezone": "UTC+02:00",
    "fileTypes": {
      "py": {
        "inserts": 1,
        "deletes": 2,
        "occurrences": 1
      }
    }
  },
  {
    "commit": "5feb2c0fecded627aa9aa99a31e6fecae7e2a713",
    "Author": "Hans Meine <hans_meine@gmx.net>",
    "Date": "2014-08-20T00:32:42-07:00",
    "orig_timezone": "UTC+02:00",
    "fileTypes": {
      "rst": {
        "inserts": 4,
        "deletes": 0,
        "occurrences": 1
      },
      "py": {
        "inserts": 1,
        "deletes": 1,
        "occurrences": 1
      }
    }
  },
  {
    "commit": "7fd13c129c61556cdefa4cb8ec22eec007ae55e2",
    "Author": "Hans Meine <hans_meine@gmx.net>",
    "Date": "2014-08-19T22:59:21-07:00",
    "orig_timezone": "UTC+02:00",
    "fileTypes": {
      "py": {
        "inserts": 173,
        "deletes": 98,
        "occurrences": 2
      }
    }
  },
  {
    "commit": "3e826a0c6b1ed5a344c6889675f731d1ac27dc32",
    "Author": "Hans Meine <hans_meine@gmx.net>",
    "Date": "2014-08-19T01:54:02-07:00",
    "orig_timezone": "UTC+02:00",
    "fileTypes": {
      "rst": {
        "inserts": 3,
        "deletes": 3,
        "occurrences": 1
      }
    }
  },
  {
    "commit": "52f1a370bd8625a66c1d4c3f3194ce9b9f6b01eb",
    "Author": "Hans Meine <hans_meine@gmx.net>",
    "Date": "2014-08-19T01:53:43-07:00",
    "orig_timezone": "UTC+02:00",
    "fileTypes": {
      "rst": {
        "inserts": 14,
        "deletes": 6,
        "occurrences": 1
      },
      "py": {
        "inserts": 12,
        "deletes": 7,
        "occurrences": 1
      }
    }
  },
  {
    "commit": "c0b2e3c297d12e8abcf695af5ed072c4067f8eb9",
    "Author": "Hans Meine <hans_meine@gmx.net>",
    "Date": "2014-08-18T23:00:17-07:00",
    "orig_timezone": "UTC+02:00",
    "fileTypes": {
      "rst": {
        "inserts": 1,
        "deletes": 0,
        "occurrences": 1
      },
      "py": {
        "inserts": 33,
        "deletes": 2,
        "occurrences": 3
      }
    }
  },
  {
    "commit": "faed7e14b5158756e4ba21b317f9f033f70ca1b7",
    "Author": "Hans Meine <hans_meine@gmx.net>",
    "Date": "2014-08-18T22:41:10-07:00",
    "orig_timezone": "UTC+02:00",
    "fileTypes": {
      "py": {
        "inserts": 18,
        "deletes": 5,
        "occurrences": 1
      }
    }
  },
  {
    "commit": "b9eeaf656517542e0a1ba14db4b0bc5bc0df3961",
    "Author": "Hans Meine <hans_meine@gmx.net>",
    "Date": "2014-08-18T22:32:16-07:00",
    "orig_timezone": "UTC+02:00",
    "fileTypes": {
      "py": {
        "inserts": 118,
        "deletes": 119,
        "occurrences": 2
      }
    }
  },
  {
    "commit": "57449ec4b0a291eb0dfb4e6006bc7f77efabfe04",
    "Author": "Hans Meine <hans_meine@gmx.net>",
    "Date": "2014-08-18T22:21:52-07:00",
    "orig_timezone": "UTC+02:00",
    "fileTypes": {
      "py": {
        "inserts": 7,
        "deletes": 3,
        "occurrences": 1
      }
    }
  },
  {
    "commit": "e6dea236b0acddf60b9fb02e2ba04c52ae0efa30",
    "Author": "Hans Meine <hans_meine@gmx.net>",
    "Date": "2014-08-18T10:25:06-07:00",
    "orig_timezone": "UTC+02:00",
    "fileTypes": {
      "py": {
        "inserts": 11,
        "deletes": 5,
        "occurrences": 1
      }
    }
  },
  {
    "commit": "8937d9d41236d7ea47f63f64464cf876248d04ae",
    "Author": "Hans Meine <hans_meine@gmx.net>",
    "Date": "2014-08-18T01:04:14-07:00",
    "orig_timezone": "UTC+02:00",
    "fileTypes": {
      "py": {
        "inserts": 153,
        "deletes": 22,
        "occurrences": 6
      }
    }
  },
  {
    "commit": "f0cfc3f9669450b8e1bd83aa8ae6b49827990d46",
    "Author": "Hans Meine <hans_meine@gmx.net>",
    "Date": "2014-08-18T01:03:08-07:00",
    "orig_timezone": "UTC+02:00",
    "fileTypes": {
      "py": {
        "inserts": 36,
        "deletes": 1,
        "occurrences": 2
      }
    }
  },
  {
    "commit": "9875ca3b266c3e13322d038570d57ed3b6cd05a5",
    "Author": "Hans Meine <hans_meine@gmx.net>",
    "Date": "2014-08-19T23:22:55-07:00",
    "orig_timezone": "UTC+02:00",
    "fileTypes": {
      "py": {
        "inserts": 1,
        "deletes": 1,
        "occurrences": 1
      }
    }
  },
  {
    "commit": "f2dd2fa2a83b634b76baa8fc8f275d596475ae91",
    "Author": "Hans Meine <hans_meine@gmx.net>",
    "Date": "2014-08-17T11:02:09-07:00",
    "orig_timezone": "UTC+02:00",
    "fileTypes": {
      "rst": {
        "inserts": 5,
        "deletes": 4,
        "occurrences": 1
      }
    }
  },
  {
    "commit": "753bd313cd679d79a6526ec39d0a8c2a3f46a676",
    "Author": "Hans Meine <hans_meine@gmx.net>",
    "Date": "2014-08-17T11:00:15-07:00",
    "orig_timezone": "UTC+02:00",
    "fileTypes": {
      "rst": {
        "inserts": 4,
        "deletes": 0,
        "occurrences": 1
      }
    }
  },
  {
    "commit": "b7d20b68bacc3f99d729b55d35d8f473f377e460",
    "Author": "Hans Meine <hans_meine@gmx.net>",
    "Date": "2014-08-17T10:47:17-07:00",
    "orig_timezone": "UTC+02:00",
    "fileTypes": {
      "py": {
        "inserts": 4,
        "deletes": 1,
        "occurrences": 1
      }
    }
  },
  {
    "commit": "668e50c121fcae6e576795c035d970008c50f003",
    "Author": "Hans Meine <hans_meine@gmx.net>",
    "Date": "2014-08-17T10:44:52-07:00",
    "orig_timezone": "UTC+02:00",
    "fileTypes": {
      "py": {
        "inserts": 1,
        "deletes": 1,
        "occurrences": 1
      }
    }
  },
  {
    "commit": "bb1f9bbb6809e44f653c2671f88950a1d5b9f39f",
    "Author": "Hans Meine <hans_meine@gmx.net>",
    "Date": "2014-04-01T12:56:37-07:00",
    "orig_timezone": "UTC+02:00",
    "fileTypes": {
      "py": {
        "inserts": 7,
        "deletes": 4,
        "occurrences": 1
      }
    }
  },
  {
    "commit": "beaa2eca4605be443f78d6dd5cd2d4be8081d0dc",
    "Author": "Hans Meine <hans_meine@gmx.net>",
    "Date": "2013-11-03T07:11:46-07:00",
    "orig_timezone": "UTC+01:00",
    "fileTypes": {
      "rst": {
        "inserts": 5,
        "deletes": 2,
        "occurrences": 1
      },
      "py": {
        "inserts": 0,
        "deletes": 1,
        "occurrences": 1
      }
    }
  },
  {
    "commit": "e070a9fa96e719acd46852df8254c24101d3e68b",
    "Author": "Hans Meine <hans_meine@gmx.net>",
    "Date": "2013-11-02T13:57:21-07:00",
    "orig_timezone": "UTC+01:00",
    "fileTypes": {
      "py": {
        "inserts": 26,
        "deletes": 12,
        "occurrences": 2
      },
      "png": {
        "inserts": 0,
        "deletes": 0,
        "occurrences": 2
      }
    }
  },
  {
    "commit": "9326e66af47b98dd1201117981a3691137916939",
    "Author": "Hans Meine <hans_meine@gmx.net>",
    "Date": "2013-11-02T04:18:35-07:00",
    "orig_timezone": "UTC+01:00",
    "fileTypes": {
      "py": {
        "inserts": 7,
        "deletes": 3,
        "occurrences": 2
      }
    }
  },
  {
    "commit": "9b0031701c36ea38a6161302a1205657100940ff",
    "Author": "Hans Meine <hans_meine@gmx.net>",
    "Date": "2013-11-02T04:13:49-07:00",
    "orig_timezone": "UTC+01:00",
    "fileTypes": {
      "rst": {
        "inserts": 12,
        "deletes": 0,
        "occurrences": 1
      }
    }
  },
  {
    "commit": "c497d7ccb405cd4cfc2558c46eb6ba131029b213",
    "Author": "Hans Meine <hans_meine@gmx.net>",
    "Date": "2013-11-02T04:02:31-07:00",
    "orig_timezone": "UTC+01:00",
    "fileTypes": {
      "py": {
        "inserts": 39,
        "deletes": 3,
        "occurrences": 2
      }
    }
  },
  {
    "commit": "d844eca0bdffc86011431567348708da8e434095",
    "Author": "Hans Meine <hans_meine@gmx.net>",
    "Date": "2013-11-01T23:27:06-07:00",
    "orig_timezone": "UTC+01:00",
    "fileTypes": {
      "py": {
        "inserts": 5,
        "deletes": 6,
        "occurrences": 3
      }
    }
  },
  {
    "commit": "765bd094180395644d2b076be53b8503b49bed4b",
    "Author": "Hans Meine <hans_meine@gmx.net>",
    "Date": "2013-11-01T22:46:24-07:00",
    "orig_timezone": "UTC+01:00",
    "fileTypes": {
      "py": {
        "inserts": 54,
        "deletes": 6,
        "occurrences": 1
      }
    }
  },
  {
    "commit": "b09f1411ae9d652db1a9594ddba3e79310c67163",
    "Author": "Hans Meine <hans_meine@gmx.net>",
    "Date": "2013-11-01T00:27:48-07:00",
    "orig_timezone": "UTC+01:00",
    "fileTypes": {
      "rst": {
        "inserts": 2,
        "deletes": 2,
        "occurrences": 1
      }
    }
  },
  {
    "commit": "e3f6df9d4e7ae9859234c25844555a06be3a5e70",
    "Author": "Hans Meine <hans_meine@gmx.net>",
    "Date": "2013-11-01T00:27:28-07:00",
    "orig_timezone": "UTC+01:00",
    "fileTypes": {
      "rst": {
        "inserts": 5,
        "deletes": 0,
        "occurrences": 1
      },
      "py": {
        "inserts": 1,
        "deletes": 1,
        "occurrences": 1
      }
    }
  },
  {
    "commit": "42077d3683a4980bdd568d051db3187149da0e39",
    "Author": "Hans Meine <hans_meine@gmx.net>",
    "Date": "2013-11-01T00:10:02-07:00",
    "orig_timezone": "UTC+01:00",
    "fileTypes": {
      "rst": {
        "inserts": 3,
        "deletes": 0,
        "occurrences": 1
      },
      "py": {
        "inserts": 3,
        "deletes": 1,
        "occurrences": 1
      }
    }
  },
  {
    "commit": "83823aa9023f52c7ba37314ac8cb0620fded7a08",
    "Author": "Hans Meine <hans_meine@gmx.net>",
    "Date": "2013-11-01T00:05:49-07:00",
    "orig_timezone": "UTC+01:00",
    "fileTypes": {
      "noexttext": {
        "inserts": 1,
        "deletes": 1,
        "occurrences": 1
      }
    }
  },
  {
    "commit": "41f95a44039aa6698b7b9b928d89b8bc295561e0",
    "Author": "Hans Meine <hans_meine@gmx.net>",
    "Date": "2013-11-01T00:03:59-07:00",
    "orig_timezone": "UTC+01:00",
    "fileTypes": {
      "py": {
        "inserts": 73,
        "deletes": 1,
        "occurrences": 2
      },
      "png": {
        "inserts": 0,
        "deletes": 0,
        "occurrences": 1
      },
      "jpg": {
        "inserts": 0,
        "deletes": 0,
        "occurrences": 2
      }
    }
  },
  {
    "commit": "de1e9d7f2e552bd806bb2dee6e37508bc8a43e46",
    "Author": "Hans Meine <hans_meine@gmx.net>",
    "Date": "2013-10-10T06:07:55-07:00",
    "orig_timezone": "UTC+02:00",
    "fileTypes": {
      "py": {
        "inserts": 1,
        "deletes": 1,
        "occurrences": 1
      }
    }
  },
  {
    "commit": "976b0c794667ba5cf5520c435fc089b4c3b34040",
    "Author": "Hans Meine <hans_meine@gmx.net>",
    "Date": "2013-10-10T05:42:28-07:00",
    "orig_timezone": "UTC+02:00",
    "fileTypes": {
      "rst": {
        "inserts": 5,
        "deletes": 3,
        "occurrences": 1
      },
      "py": {
        "inserts": 2,
        "deletes": 2,
        "occurrences": 1
      }
    }
  },
  {
    "commit": "291d7abfb01f8f284dec2ad24e52b456f0eeefd2",
    "Author": "Hans Meine <hans_meine@gmx.net>",
    "Date": "2013-10-10T02:46:32-07:00",
    "orig_timezone": "UTC+02:00",
    "fileTypes": {
      "noexttext": {
        "inserts": 11,
        "deletes": 6,
        "occurrences": 2
      }
    }
  },
  {
    "commit": "e7148043818ce7ca011af9625f57055f509d98a3",
    "Author": "Hans Meine <hans_meine@gmx.net>",
    "Date": "2013-10-10T02:28:45-07:00",
    "orig_timezone": "UTC+02:00",
    "fileTypes": {
      "rst": {
        "inserts": 5,
        "deletes": 0,
        "occurrences": 1
      },
      "py": {
        "inserts": 1,
        "deletes": 1,
        "occurrences": 1
      }
    }
  },
  {
    "commit": "615c5eb85985f25521501207c614eaef675f3f4f",
    "Author": "Hans Meine <hans_meine@gmx.net>",
    "Date": "2013-10-10T00:55:16-07:00",
    "orig_timezone": "UTC+02:00",
    "fileTypes": {
      "py": {
        "inserts": 1,
        "deletes": 0,
        "occurrences": 1
      }
    }
  },
  {
    "commit": "6e63e4473544452081db7db85a9b1d96532db6b1",
    "Author": "Hans Meine <hans_meine@gmx.net>",
    "Date": "2013-10-10T00:54:23-07:00",
    "orig_timezone": "UTC+02:00",
    "fileTypes": {
      "py": {
        "inserts": 2,
        "deletes": 2,
        "occurrences": 1
      }
    }
  },
  {
    "commit": "2cc19fb05a756e1384d7696e1f6836b3cb794039",
    "Author": "Hans Meine <hans_meine@gmx.net>",
    "Date": "2013-10-10T00:53:57-07:00",
    "orig_timezone": "UTC+02:00",
    "fileTypes": {
      "py": {
        "inserts": 3,
        "deletes": 3,
        "occurrences": 1
      }
    }
  },
  {
    "commit": "a7817d93861f59e2050a882bb76b79162d0d5167",
    "Author": "Hans Meine <hans_meine@gmx.net>",
    "Date": "2013-10-10T00:53:26-07:00",
    "orig_timezone": "UTC+02:00",
    "fileTypes": {
      "py": {
        "inserts": 2,
        "deletes": 2,
        "occurrences": 1
      }
    }
  },
  {
    "commit": "c82aa7ab4d81de4f6e3d1b643e0c7645694fa8c7",
    "Author": "Hans Meine <hans_meine@gmx.net>",
    "Date": "2013-10-09T22:16:59-07:00",
    "orig_timezone": "UTC+02:00",
    "fileTypes": {
      "py": {
        "inserts": 2,
        "deletes": 1,
        "occurrences": 1
      }
    }
  },
  {
    "commit": "e07231aa653f6ec855e340016060f592e70ff9d5",
    "Author": "Hans Meine <hans_meine@gmx.net>",
    "Date": "2013-10-09T22:15:59-07:00",
    "orig_timezone": "UTC+02:00",
    "fileTypes": {
      "py": {
        "inserts": 2,
        "deletes": 1,
        "occurrences": 1
      }
    }
  },
  {
    "commit": "132b420159affa293612be3beaac0c9e6a612a57",
    "Author": "Hans Meine <hans_meine@gmx.net>",
    "Date": "2013-10-09T22:14:43-07:00",
    "orig_timezone": "UTC+02:00",
    "fileTypes": {
      "h": {
        "inserts": 6,
        "deletes": 2,
        "occurrences": 1
      }
    }
  },
  {
    "commit": "95017a1fdde17bb320f70d23d4f0d75c9c54b418",
    "Author": "Hans Meine <hans_meine@gmx.net>",
    "Date": "2013-06-26T12:27:16-07:00",
    "orig_timezone": "UTC+02:00",
    "fileTypes": {
      "txt": {
        "inserts": 1,
        "deletes": 1,
        "occurrences": 1
      },
      "rst": {
        "inserts": 1,
        "deletes": 2,
        "occurrences": 1
      },
      "py": {
        "inserts": 1,
        "deletes": 1,
        "occurrences": 1
      }
    }
  },
  {
    "commit": "90fe6cff44b94826849194cff190cd57ff8f4969",
    "Author": "Hans Meine <hans_meine@gmx.net>",
    "Date": "2013-06-26T12:23:41-07:00",
    "orig_timezone": "UTC+02:00",
    "fileTypes": {
      "rst": {
        "inserts": 8,
        "deletes": 8,
        "occurrences": 2
      }
    }
  },
  {
    "commit": "1da030394a8455a5d33b7e2ee3ec4b39b9e839e8",
    "Author": "Hans Meine <hans_meine@gmx.net>",
    "Date": "2013-06-26T12:16:15-07:00",
    "orig_timezone": "UTC+02:00",
    "fileTypes": {
      "rst": {
        "inserts": 0,
        "deletes": 0,
        "occurrences": 1
      }
    }
  },
  {
    "commit": "c296e907a10c44ae8758af5a6c9fbbf09ccb99da",
    "Author": "Hans Meine <hans_meine@gmx.net>",
    "Date": "2012-11-22T00:39:46-07:00",
    "orig_timezone": "UTC+01:00",
    "fileTypes": {
      "rst": {
        "inserts": 1,
        "deletes": 0,
        "occurrences": 1
      },
      "py": {
        "inserts": 7,
        "deletes": 2,
        "occurrences": 1
      }
    }
  },
  {
    "commit": "ee900e5b996187fd3b5b45da14a558cd79e70909",
    "Author": "Hans Meine <hans_meine@gmx.net>",
    "Date": "2012-11-09T13:48:03-07:00",
    "orig_timezone": "UTC+01:00",
    "fileTypes": {
      "rst": {
        "inserts": 5,
        "deletes": 0,
        "occurrences": 1
      },
      "py": {
        "inserts": 1,
        "deletes": 1,
        "occurrences": 1
      }
    }
  },
  {
    "commit": "f07b3e0710332a88133f28486744f21540bf4a74",
    "Author": "Hans Meine <hans_meine@gmx.net>",
    "Date": "2012-11-09T13:46:52-07:00",
    "orig_timezone": "UTC+01:00",
    "fileTypes": {
      "py": {
        "inserts": 8,
        "deletes": 7,
        "occurrences": 1
      }
    }
  },
  {
    "commit": "aa4bccc19fc62314c04aa0e31d958844bc2b5b9a",
    "Author": "Hans Meine <hans_meine@gmx.net>",
    "Date": "2012-09-11T23:38:41-07:00",
    "orig_timezone": "UTC+02:00",
    "fileTypes": {
      "h": {
        "inserts": 31,
        "deletes": 31,
        "occurrences": 1
      },
      "py": {
        "inserts": 571,
        "deletes": 571,
        "occurrences": 4
      },
      "sip": {
        "inserts": 4,
        "deletes": 4,
        "occurrences": 1
      }
    }
  },
  {
    "commit": "3c215f11b3f25f449c3217ad35acef7319740aa9",
    "Author": "Hans Meine <hans_meine@gmx.net>",
    "Date": "2012-09-11T23:30:00-07:00",
    "orig_timezone": "UTC+02:00",
    "fileTypes": {
      "sip": {
        "inserts": 1,
        "deletes": 1,
        "occurrences": 1
      }
    }
  },
  {
    "commit": "f19b14630bf844a4c2746439da0aab0e5ae28588",
    "Author": "Hans Meine <hans.meine@mevis.fraunhofer.de>",
    "Date": "2012-05-23T01:03:16-07:00",
    "orig_timezone": "UTC+02:00",
    "fileTypes": {
      "h": {
        "inserts": 5,
        "deletes": 2,
        "occurrences": 1
      }
    }
  },
  {
    "commit": "6c9c343f6bb1f76f243d6e06dbd8b1530f41f071",
    "Author": "Hans Meine <hans.meine@mevis.fraunhofer.de>",
    "Date": "2012-05-23T01:00:34-07:00",
    "orig_timezone": "UTC+02:00",
    "fileTypes": {
      "py": {
        "inserts": 33,
        "deletes": 2,
        "occurrences": 1
      }
    }
  },
  {
    "commit": "06db0e68866dbe350f87a09e41eb339301c35fcc",
    "Author": "Hans Meine <hans.meine@mevis.fraunhofer.de>",
    "Date": "2012-04-20T02:59:21-07:00",
    "orig_timezone": "UTC+02:00",
    "fileTypes": {
      "h": {
        "inserts": 45,
        "deletes": 0,
        "occurrences": 1
      },
      "sip": {
        "inserts": 4,
        "deletes": 36,
        "occurrences": 1
      },
      "py": {
        "inserts": 61,
        "deletes": 60,
        "occurrences": 1
      }
    }
  },
  {
    "commit": "6d711f84b0c78a2b8ba086f9d7c270887fae176d",
    "Author": "Hans Meine <hans_meine@gmx.net>",
    "Date": "2011-08-05T03:22:03-07:00",
    "orig_timezone": "UTC+02:00",
    "fileTypes": {
      "py": {
        "inserts": 16,
        "deletes": 3,
        "occurrences": 1
      }
    }
  },
  {
    "commit": "1e14e92769dd19ea7bff554edccacdb29d4de90f",
    "Author": "Hans Meine <hans_meine@gmx.net>",
    "Date": "2010-12-20T13:48:42-07:00",
    "orig_timezone": "UTC+01:00",
    "fileTypes": {
      "py": {
        "inserts": 3,
        "deletes": 2,
        "occurrences": 1
      }
    }
  },
  {
    "commit": "276f8645015a10b3b3d3607ce3362741e3bc32e4",
    "Author": "Hans Meine <meine@informatik.uni-hamburg.de>",
    "Date": "2010-11-05T02:58:20-07:00",
    "orig_timezone": "UTC+01:00",
    "fileTypes": {
      "py": {
        "inserts": 2,
        "deletes": 2,
        "occurrences": 1
      }
    }
  },
  {
    "commit": "4bffeb5e981ff7bddd999c43fb18f44666c2d6b7",
    "Author": "Hans Meine <meine@informatik.uni-hamburg.de>",
    "Date": "2010-09-28T07:52:44-07:00",
    "orig_timezone": "UTC+02:00",
    "fileTypes": {
      "py": {
        "inserts": 22,
        "deletes": 19,
        "occurrences": 1
      }
    }
  },
  {
    "commit": "b55598af36006289eb2c49c92044fb52be2712c8",
    "Author": "Hans Meine <meine@informatik.uni-hamburg.de>",
    "Date": "2010-06-09T00:19:59-07:00",
    "orig_timezone": "UTC+02:00",
    "fileTypes": {
      "rst": {
        "inserts": 2,
        "deletes": 1,
        "occurrences": 1
      },
      "py": {
        "inserts": 1,
        "deletes": 1,
        "occurrences": 1
      }
    }
  },
  {
    "commit": "09dc4078dbccb6e16e409c8d0aa45ae32d147094",
    "Author": "Hans Meine <meine@informatik.uni-hamburg.de>",
    "Date": "2010-06-08T10:07:07-07:00",
    "orig_timezone": "UTC+02:00",
    "fileTypes": {
      "py": {
        "inserts": 15,
        "deletes": 6,
        "occurrences": 1
      }
    }
  },
  {
    "commit": "bc0ccdbc70705b6a39ce3043be503af008c33920",
    "Author": "Hans Meine <meine@informatik.uni-hamburg.de>",
    "Date": "2010-06-08T10:03:22-07:00",
    "orig_timezone": "UTC+02:00",
    "fileTypes": {
      "rst": {
        "inserts": 1,
        "deletes": 1,
        "occurrences": 1
      }
    }
  },
  {
    "commit": "a57e8612d1f7ea99f2745efa6d114112c282edde",
    "Author": "Hans Meine <meine@informatik.uni-hamburg.de>",
    "Date": "2010-02-12T09:32:41-07:00",
    "orig_timezone": "UTC+01:00",
    "fileTypes": {
      "rst": {
        "inserts": 3,
        "deletes": 0,
        "occurrences": 1
      },
      "py": {
        "inserts": 35,
        "deletes": 9,
        "occurrences": 2
      }
    }
  },
  {
    "commit": "31d1089c91f0a258f9d60179cc60eec7ef5bebcb",
    "Author": "Hans Meine <meine@informatik.uni-hamburg.de>",
    "Date": "2010-02-12T09:32:08-07:00",
    "orig_timezone": "UTC+01:00",
    "fileTypes": {
      "noexttext": {
        "inserts": 1,
        "deletes": 1,
        "occurrences": 1
      }
    }
  },
  {
    "commit": "2a8b2879faea661b2d775738913d22f98737acc3",
    "Author": "Hans Meine <meine@informatik.uni-hamburg.de>",
    "Date": "2010-02-12T09:31:25-07:00",
    "orig_timezone": "UTC+01:00",
    "fileTypes": {
      "py": {
        "inserts": 5,
        "deletes": 1,
        "occurrences": 1
      }
    }
  },
  {
    "commit": "b65ef15d98b6b045093be447ee9fb4228f9a33b2",
    "Author": "Hans Meine <meine@informatik.uni-hamburg.de>",
    "Date": "2010-01-13T08:29:20-07:00",
    "orig_timezone": "UTC+01:00",
    "fileTypes": {
      "py": {
        "inserts": 2,
        "deletes": 2,
        "occurrences": 1
      },
      "rst": {
        "inserts": 10,
        "deletes": 0,
        "occurrences": 1
      }
    }
  },
  {
    "commit": "fe30cf27fc9a2c85f3b149ca05cda67ffe9828ff",
    "Author": "Hans Meine <meine@informatik.uni-hamburg.de>",
    "Date": "2010-01-13T08:00:06-07:00",
    "orig_timezone": "UTC+01:00",
    "fileTypes": {
      "py": {
        "inserts": 3,
        "deletes": 3,
        "occurrences": 1
      }
    }
  },
  {
    "commit": "e998e5179489e9a43f2e3cc52066e658c49714e9",
    "Author": "Hans Meine <meine@informatik.uni-hamburg.de>",
    "Date": "2010-01-07T09:26:33-07:00",
    "orig_timezone": "UTC+01:00",
    "fileTypes": {
      "txt": {
        "inserts": 2,
        "deletes": 1,
        "occurrences": 1
      }
    }
  },
  {
    "commit": "202d18979e110b46ad1978f02122cf12e4fac9c9",
    "Author": "Hans Meine <meine@informatik.uni-hamburg.de>",
    "Date": "2010-01-07T08:11:52-07:00",
    "orig_timezone": "UTC+01:00",
    "fileTypes": {
      "py": {
        "inserts": 3,
        "deletes": 1,
        "occurrences": 1
      }
    }
  },
  {
    "commit": "1fe0ac2f2916ac682ce1be262b94bee86fdfee69",
    "Author": "Hans Meine <meine@informatik.uni-hamburg.de>",
    "Date": "2010-01-07T08:11:35-07:00",
    "orig_timezone": "UTC+01:00",
    "fileTypes": {
      "py": {
        "inserts": 4,
        "deletes": 7,
        "occurrences": 1
      }
    }
  },
  {
    "commit": "e422cc991171b83b224a6c26f434d9073f9b796a",
    "Author": "Hans Meine <meine@informatik.uni-hamburg.de>",
    "Date": "2009-12-08T02:55:16-07:00",
    "orig_timezone": "UTC+01:00",
    "fileTypes": {
      "py": {
        "inserts": 43,
        "deletes": 11,
        "occurrences": 1
      }
    }
  },
  {
    "commit": "9f9a91f1b2a153aeea4dbd8e56ac474b11045552",
    "Author": "Hans Meine <meine@informatik.uni-hamburg.de>",
    "Date": "2009-12-08T01:52:09-07:00",
    "orig_timezone": "UTC+01:00",
    "fileTypes": {
      "rst": {
        "inserts": 6,
        "deletes": 3,
        "occurrences": 1
      },
      "py": {
        "inserts": 2,
        "deletes": 2,
        "occurrences": 1
      }
    }
  },
  {
    "commit": "c9a89015c321a38fbbfbbb7ce8a05cd713c019cb",
    "Author": "Ullrich Koethe <ullrich.koethe@iwr.uni-heidelberg.de>",
    "Date": "2009-12-04T08:48:01-07:00",
    "orig_timezone": "UTC+01:00",
    "fileTypes": {
      "py": {
        "inserts": 3,
        "deletes": 1,
        "occurrences": 1
      }
    }
  },
  {
    "commit": "864b99a73daf3e5f1c7a2aea1bc9b888241a41cd",
    "Author": "Hans Meine <meine@informatik.uni-hamburg.de>",
    "Date": "2009-12-04T05:26:35-07:00",
    "orig_timezone": "UTC+01:00",
    "fileTypes": {
      "txt": {
        "inserts": 14,
        "deletes": 0,
        "occurrences": 1
      }
    }
  },
  {
    "commit": "8ce2ee1f3b7802e26e427e7cb4b5f206c79c0da6",
    "Author": "Hans Meine <meine@informatik.uni-hamburg.de>",
    "Date": "2009-12-04T05:05:16-07:00",
    "orig_timezone": "UTC+01:00",
    "fileTypes": {
      "py": {
        "inserts": 0,
        "deletes": 0,
        "occurrences": 3
      }
    }
  },
  {
    "commit": "b2dcfe8bcd43ebcc2bfffa748340235db5b4d2e9",
    "Author": "Hans Meine <meine@informatik.uni-hamburg.de>",
    "Date": "2009-12-04T05:01:03-07:00",
    "orig_timezone": "UTC+01:00",
    "fileTypes": {
      "py": {
        "inserts": 19,
        "deletes": 5,
        "occurrences": 1
      }
    }
  },
  {
    "commit": "c98847a67596e55b59deb79515f604401133aa7e",
    "Author": "Ullrich Koethe <ullrich.koethe@iwr.uni-heidelberg.de>",
    "Date": "2009-12-04T04:08:21-07:00",
    "orig_timezone": "UTC+01:00",
    "fileTypes": {
      "py": {
        "inserts": 1,
        "deletes": 1,
        "occurrences": 1
      }
    }
  },
  {
    "commit": "bbe42721405de6051bebf19a91d8c492ba374342",
    "Author": "Hans Meine <meine@informatik.uni-hamburg.de>",
    "Date": "2009-12-02T09:15:10-07:00",
    "orig_timezone": "UTC+01:00",
    "fileTypes": {
      "txt": {
        "inserts": 65,
        "deletes": 0,
        "occurrences": 2
      },
      "rst": {
        "inserts": 3,
        "deletes": 1,
        "occurrences": 1
      }
    }
  },
  {
    "commit": "2c94b03613d067131ea36a855c0b2f3bb41441da",
    "Author": "Hans Meine <meine@informatik.uni-hamburg.de>",
    "Date": "2009-12-02T09:05:33-07:00",
    "orig_timezone": "UTC+01:00",
    "fileTypes": {
      "py": {
        "inserts": 7,
        "deletes": 7,
        "occurrences": 2
      },
      "rst": {
        "inserts": 3,
        "deletes": 3,
        "occurrences": 1
      }
    }
  },
  {
    "commit": "b998eea23977f34ff59bf4ce21b0a95b6269fc13",
    "Author": "Hans Meine <meine@informatik.uni-hamburg.de>",
    "Date": "2009-12-02T08:57:20-07:00",
    "orig_timezone": "UTC+01:00",
    "fileTypes": {
      "py": {
        "inserts": 2,
        "deletes": 2,
        "occurrences": 1
      }
    }
  },
  {
    "commit": "31c9fca90740072fa4ca98d777c99af5ba36d521",
    "Author": "Hans Meine <meine@informatik.uni-hamburg.de>",
    "Date": "2009-12-02T08:52:37-07:00",
    "orig_timezone": "UTC+01:00",
    "fileTypes": {
      "noexttext": {
        "inserts": 90,
        "deletes": 0,
        "occurrences": 2
      },
      "py": {
        "inserts": 265,
        "deletes": 17,
        "occurrences": 3
      },
      "rst": {
        "inserts": 114,
        "deletes": 0,
        "occurrences": 1
      },
      "bat": {
        "inserts": 113,
        "deletes": 0,
        "occurrences": 1
      }
    }
  },
  {
    "commit": "3de9b925058364629da612c0250183404f95b5f7",
    "Author": "Hans Meine <meine@informatik.uni-hamburg.de>",
    "Date": "2009-11-30T10:02:37-07:00",
    "orig_timezone": "UTC+01:00",
    "fileTypes": {
      "py": {
        "inserts": 41,
        "deletes": 1,
        "occurrences": 1
      }
    }
  },
  {
    "commit": "147ef75479f7f1a5aa708dd27476063bf51fecae",
    "Author": "Hans Meine <meine@informatik.uni-hamburg.de>",
    "Date": "2009-11-30T09:10:41-07:00",
    "orig_timezone": "UTC+01:00",
    "fileTypes": {
      "py": {
        "inserts": 2,
        "deletes": 0,
        "occurrences": 1
      }
    }
  },
  {
    "commit": "53ac0ad574fb0538cc9f89eb9cbf68878ee32435",
    "Author": "Hans Meine <meine@informatik.uni-hamburg.de>",
    "Date": "2009-11-30T09:05:30-07:00",
    "orig_timezone": "UTC+01:00",
    "fileTypes": {
      "sip": {
        "inserts": 4,
        "deletes": 0,
        "occurrences": 1
      }
    }
  },
  {
    "commit": "e23831ce150d2eb456b950f8fded90fda2d91b0e",
    "Author": "Hans Meine <meine@informatik.uni-hamburg.de>",
    "Date": "2009-10-27T03:10:36-07:00",
    "orig_timezone": "UTC+01:00",
    "fileTypes": {
      "py": {
        "inserts": 1,
        "deletes": 10,
        "occurrences": 1
      }
    }
  },
  {
    "commit": "7e09511fbcd9755d84a530a6771b7bd5c141d4af",
    "Author": "Hans Meine <meine@informatik.uni-hamburg.de>",
    "Date": "2009-10-27T03:08:34-07:00",
    "orig_timezone": "UTC+01:00",
    "fileTypes": {
      "py": {
        "inserts": 23,
        "deletes": 10,
        "occurrences": 1
      }
    }
  },
  {
    "commit": "fd2a05aee3583ff817066bb3bf8824ea41168f5a",
    "Author": "Hans Meine <meine@informatik.uni-hamburg.de>",
    "Date": "2009-10-26T05:49:31-07:00",
    "orig_timezone": "UTC+01:00",
    "fileTypes": {
      "noexttext": {
        "inserts": 2,
        "deletes": 1,
        "occurrences": 1
      },
      "py": {
        "inserts": 10,
        "deletes": 3,
        "occurrences": 1
      }
    }
  },
  {
    "commit": "5f8711da189c3a401f5e42aa3b995c50e91e7441",
    "Author": "Hans Meine <meine@informatik.uni-hamburg.de>",
    "Date": "2009-10-26T04:35:01-07:00",
    "orig_timezone": "UTC+01:00",
    "fileTypes": {
      "py": {
        "inserts": 191,
        "deletes": 1,
        "occurrences": 2
      }
    }
  },
  {
    "commit": "0e63e7345952e89417ded4107e95c66d4a49942f",
    "Author": "Hans Meine <meine@informatik.uni-hamburg.de>",
    "Date": "2009-10-26T03:28:01-07:00",
    "orig_timezone": "UTC+01:00",
    "fileTypes": {
      "py": {
        "inserts": 21,
        "deletes": 0,
        "occurrences": 2
      }
    }
  },
  {
    "commit": "220a8b2320bde839047a2000266db90bdb97242e",
    "Author": "Hans Meine <meine@informatik.uni-hamburg.de>",
    "Date": "2009-10-26T03:08:23-07:00",
    "orig_timezone": "UTC+01:00",
    "fileTypes": {
      "py": {
        "inserts": 49,
        "deletes": 7,
        "occurrences": 2
      }
    }
  },
  {
    "commit": "2eb6af373178a79961b8df096badf6842dab1864",
    "Author": "Hans Meine <meine@informatik.uni-hamburg.de>",
    "Date": "2009-10-23T05:21:34-07:00",
    "orig_timezone": "UTC+02:00",
    "fileTypes": {
      "py": {
        "inserts": 108,
        "deletes": 0,
        "occurrences": 2
      }
    }
  },
  {
    "commit": "7e09f731b56e1ad2bed424af9ad9f7e820bb3020",
    "Author": "Hans Meine <meine@informatik.uni-hamburg.de>",
    "Date": "2009-10-23T02:26:11-07:00",
    "orig_timezone": "UTC+02:00",
    "fileTypes": {
      "py": {
        "inserts": 69,
        "deletes": 1,
        "occurrences": 2
      }
    }
  },
  {
    "commit": "81f41e0cd2f2fb19f74da7dfba4b033b2c950269",
    "Author": "Hans Meine <meine@informatik.uni-hamburg.de>",
    "Date": "2009-10-23T01:46:46-07:00",
    "orig_timezone": "UTC+02:00",
    "fileTypes": {
      "py": {
        "inserts": 18,
        "deletes": 2,
        "occurrences": 2
      }
    }
  },
  {
    "commit": "da7c3b47387f69502bd81d1b95b73a93c8910a91",
    "Author": "Hans Meine <meine@informatik.uni-hamburg.de>",
    "Date": "2009-10-23T01:37:43-07:00",
    "orig_timezone": "UTC+02:00",
    "fileTypes": {
      "py": {
        "inserts": 36,
        "deletes": 1,
        "occurrences": 3
      }
    }
  },
  {
    "commit": "3035826c7344062e2d96ae7098af9c6ce9e869b7",
    "Author": "Hans Meine <meine@informatik.uni-hamburg.de>",
    "Date": "2009-10-23T01:36:17-07:00",
    "orig_timezone": "UTC+02:00",
    "fileTypes": {
      "py": {
        "inserts": 10,
        "deletes": 11,
        "occurrences": 1
      }
    }
  },
  {
    "commit": "eddbd1343f849a3f3df6c24207cf677aab697772",
    "Author": "Hans Meine <meine@informatik.uni-hamburg.de>",
    "Date": "2009-10-23T01:19:27-07:00",
    "orig_timezone": "UTC+02:00",
    "fileTypes": {
      "noexttext": {
        "inserts": 1,
        "deletes": 2,
        "occurrences": 1
      },
      "py": {
        "inserts": 36,
        "deletes": 55,
        "occurrences": 2
      }
    }
  },
  {
    "commit": "f8df4d2ba24242d2fa570d50e7ee156d1f4e6f34",
    "Author": "Hans Meine <meine@informatik.uni-hamburg.de>",
    "Date": "2009-10-22T08:42:20-07:00",
    "orig_timezone": "UTC+02:00",
    "fileTypes": {
      "sip": {
        "inserts": 15,
        "deletes": 4,
        "occurrences": 1
      },
      "py": {
        "inserts": 24,
        "deletes": 0,
        "occurrences": 1
      }
    }
  },
  {
    "commit": "28c3ab3303b2509a312ebae8381deaec4f999569",
    "Author": "Hans Meine <meine@informatik.uni-hamburg.de>",
    "Date": "2009-10-22T08:13:11-07:00",
    "orig_timezone": "UTC+02:00",
    "fileTypes": {
      "sip": {
        "inserts": 18,
        "deletes": 1,
        "occurrences": 1
      },
      "py": {
        "inserts": 49,
        "deletes": 11,
        "occurrences": 1
      }
    }
  },
  {
    "commit": "0373e9ab4be697a3436dabc49d304659f481f355",
    "Author": "Hans Meine <meine@informatik.uni-hamburg.de>",
    "Date": "2009-10-22T07:55:23-07:00",
    "orig_timezone": "UTC+02:00",
    "fileTypes": {
      "sip": {
        "inserts": 1,
        "deletes": 1,
        "occurrences": 1
      },
      "py": {
        "inserts": 23,
        "deletes": 1,
        "occurrences": 1
      }
    }
  },
  {
    "commit": "774b9fcf42e3f9bdc63721d283fe0ffbf365cbf2",
    "Author": "Hans Meine <meine@informatik.uni-hamburg.de>",
    "Date": "2009-10-22T07:48:37-07:00",
    "orig_timezone": "UTC+02:00",
    "fileTypes": {
      "py": {
        "inserts": 22,
        "deletes": 0,
        "occurrences": 1
      }
    }
  }
]